markdown2dash/__init__.py
markdown2dash/src/decorators.py
markdown2dash/src/directives/admonition.py
markdown2dash/src/directives/base.py
markdown2dash/src/directives/divider.py
markdown2dash/src/directives/exec.py
markdown2dash/src/directives/image.py
markdown2dash/src/directives/kwargs.py
markdown2dash/src/directives/source.py
markdown2dash/src/directives/toc.py
markdown2dash/src/parser.py
markdown2dash/src/renderer.py
markdown2dash/src/utils.py
markdown2dash-0.1.1.dist-info/LICENSE
markdown2dash-0.1.1.dist-info/WHEEL
markdown2dash-0.1.1.dist-info/METADATA
markdown2dash-0.1.1.dist-info/RECORD
