Metadata-Version: 2.1
Name: markdown2dash
Version: 0.1.1
Summary: Render markdown into a dash layout using dash-mantine-components
Home-page: https://github.com/snehilvj/markdown2dash
License: MIT
Keywords: dash,plotly,documentation,markdown,dash-mantine-components,dmc
Author: Snehil Vijay
Author-email: snehilvj@outlook.com
Requires-Python: >=3.7
Classifier: Environment :: Web Environment
Classifier: Framework :: Dash
Classifier: Framework :: Flask
Classifier: Intended Audience :: Developers
Classifier: Intended Audience :: Education
Classifier: Intended Audience :: Financial and Insurance Industry
Classifier: Intended Audience :: Healthcare Industry
Classifier: Intended Audience :: Manufacturing
Classifier: Intended Audience :: Science/Research
Classifier: License :: OSI Approved :: MIT License
Classifier: Programming Language :: Python
Classifier: Programming Language :: Python :: 3
Classifier: Programming Language :: Python :: 3.10
Classifier: Programming Language :: Python :: 3.7
Classifier: Programming Language :: Python :: 3.8
Classifier: Programming Language :: Python :: 3.9
Classifier: Topic :: Database :: Front-Ends
Classifier: Topic :: Office/Business :: Financial :: Spreadsheet
Classifier: Topic :: Scientific/Engineering :: Visualization
Classifier: Topic :: Software Development :: Libraries :: Application Frameworks
Classifier: Topic :: Software Development :: Widget Sets
Requires-Dist: dash (>=2,<3)
Requires-Dist: dash-iconify (>=0.1.2,<0.2.0)
Requires-Dist: dash-mantine-components (>=0.14,<0.15)
Requires-Dist: gunicorn (>=21.2.0,<22.0.0)
Requires-Dist: jsonpath (>=0.82,<0.83)
Requires-Dist: mistune (>=3.0.1,<4.0.0)
Project-URL: Documentation, https://github.com/snehilvj/markdown2dash
Project-URL: Repository, https://github.com/snehilvj/markdown2dash
